Metadata-Version: 2.1
Name: imgread
Version: 0.0.1
Summary: Docs from jupyter notebooks.
Home-page: https://github.com/ayasyrev/imgread
Author: Yasyrev Andrei
Author-email: a.yasyrev@gmail.com
License: apache2
Classifier: Programming Language :: Python :: 3
Classifier: License :: OSI Approved :: Apache Software License
Classifier: Operating System :: OS Independent
Requires-Python: >=3.8
Provides-Extra: test
License-File: LICENSE
